dialect/__init__.py
dialect/__main__.py
dialect/context.py
dialect/engine.py
dialect/error.py
dialect/lex.py
dialect/macro.py
dialect/main.py
dialect/parse.py
dialect/parsetab.py
dialect/stdlib.py
dialect/util.py
dialect-0.1.13.dist-info/LICENSE
dialect-0.1.13.dist-info/METADATA
dialect-0.1.13.dist-info/WHEEL
dialect-0.1.13.dist-info/entry_points.txt
dialect-0.1.13.dist-info/top_level.txt
dialect-0.1.13.dist-info/RECORD
