Metadata-Version: 2.1
Name: dialect
Version: 0.1.13
Summary: UNKNOWN
Home-page: https://github.com/ACov96/dialect/tree/master
Author: Alex Covington
Author-email: alex@covington.tech
License: MIT
Platform: UNKNOWN
Requires-Dist: ply (==3.11)
